hdl/simple_datapath.v
// Datapath genérico para SimpleCPU
// Contiene: Banco de registros, ALU, Shifter

module simple_datapath #(
    parameter BIT_WIDTH = 16,
    parameter NUM_REGS = 16
)(
    input wire clk,
    input wire rst_n,
    
    // Señales de control
    input wire [2:0] opcode,
    input wire [3:0] reg_a_sel,
    input wire [3:0] reg_b_sel,
    input wire [3:0] dest_reg,
    input wire reg_write,
    
    // Entrada de datos externos
    input wire load_operands,
    input wire [BIT_WIDTH-1:0] operand_a_in,
    input wire [BIT_WIDTH-1:0] operand_b_in,
    
    // Salidas
    output wire [BIT_WIDTH-1:0] reg_a_val,
    output wire [BIT_WIDTH-1:0] reg_b_val,
    output wire [BIT_WIDTH-1:0] result_out,
    output wire zero_flag,
    output wire equal_flag,
    output wire greater_flag
);

    // OpCodes
    localparam OP_ADD = 3'd0;
    localparam OP_SUB = 3'd1;
    localparam OP_SHL = 3'd2;
    localparam OP_SHR = 3'd3;
    localparam OP_MOV = 3'd4;
    localparam OP_BGT = 3'd5;
    localparam OP_BEQ = 3'd6;
    localparam OP_HALT = 3'd7;

    // Banco de registros
    reg [BIT_WIDTH-1:0] registers [0:NUM_REGS-1];
    
    // Registros constantes (solo lectura)
    localparam NUM_CONST_REGS = 8;
    
    // Valores de registros seleccionados
    assign reg_a_val = registers[reg_a_sel];
    assign reg_b_val = registers[reg_b_sel];
    
    // Resultado de la ALU
    reg [BIT_WIDTH-1:0] alu_result;
    
    // Flags
    assign zero_flag = (reg_b_val == 0);
    assign equal_flag = (reg_a_val == reg_b_val);
    assign greater_flag = (reg_a_val > reg_b_val);
    
    // Lógica de ALU (combinacional)
    always @(*) begin
        case (opcode)
            OP_ADD: alu_result = reg_a_val + reg_b_val;
            OP_SUB: alu_result = reg_a_val - reg_b_val;
            OP_SHL: alu_result = reg_a_val << (reg_b_val[3:0]);
            OP_SHR: alu_result = reg_a_val >> (reg_b_val[3:0]);
            OP_MOV: alu_result = reg_a_val;
            default: alu_result = 0;
        endcase
    end
    
    assign result_out = alu_result;
    
    // Inicialización y escritura de registros
    integer i;
    always @(posedge clk or negedge rst_n) begin
        if (!rst_n) begin
            // Reset: inicializar registros constantes
            registers[0] <= 0;   // R0 = 0
            registers[1] <= 1;   // R1 = 1
            registers[2] <= 2;   // R2 = 2
            registers[3] <= 4;   // R3 = 4
            registers[4] <= 8;   // R4 = 8
            registers[5] <= 16;  // R5 = 16
            registers[6] <= 32;  // R6 = 32
            registers[7] <= 64;  // R7 = 64
            
            // Reset registros escribibles
            for (i = NUM_CONST_REGS; i < NUM_REGS; i = i + 1) begin
                registers[i] <= 0;
            end
        end else begin
            // Cargar operandos externos
            if (load_operands) begin
                registers[8] <= operand_a_in;   // R8 = A (multiplicando)
                registers[9] <= operand_b_in;   // R9 = B (multiplicador)
                registers[10] <= 0;             // R10 = P (producto)
            end
            // Escribir resultado en registro destino (si es escribible)
            else if (reg_write && dest_reg >= NUM_CONST_REGS) begin
                registers[dest_reg] <= alu_result;
            end
        end
    end

endmodule

hdl/simple_control.v
// Unidad de Control para SimpleCPU (con pipeline FETCH/EXECUTE)
// Lee instrucciones de ROM y genera señales de control

module simple_control #(
    parameter PROGRAM_SIZE = 16,
    parameter PROGRAM_FILE = "program.mem"
)(
    input wire clk,
    input wire rst_n,
    input wire start,
    
    // Flags del datapath (evaluados después de aplicar selectores)
    input wire zero_flag,
    input wire equal_flag,
    input wire greater_flag,
    
    // Señales de control hacia el datapath
    output reg [2:0] opcode,
    output reg [3:0] reg_a_sel,
    output reg [3:0] reg_b_sel,
    output reg [3:0] dest_reg,
    output reg reg_write,
    output reg load_operands,
    
    // Estado
    output reg [3:0] pc,
    output reg done
);

    // OpCodes
    localparam OP_ADD = 3'd0;
    localparam OP_SUB = 3'd1;
    localparam OP_SHL = 3'd2;
    localparam OP_SHR = 3'd3;
    localparam OP_MOV = 3'd4;
    localparam OP_BGT = 3'd5;
    localparam OP_BEQ = 3'd6;
    localparam OP_HALT = 3'd7;
    
    // Memoria de programa (ROM)
    // Formato: [OpCode(3)][RegA(4)][RegB(4)][Dest1(4)][Dest2(4)] = 19 bits
    reg [18:0] program_rom [0:PROGRAM_SIZE-1];
    
    // Instrucción actual
    wire [18:0] instruction;
    wire [2:0] instr_opcode;
    wire [3:0] instr_reg_a;
    wire [3:0] instr_reg_b;
    wire [3:0] instr_dest1;
    wire [3:0] instr_dest2;
    
    // Decodificar instrucción
    assign instruction = program_rom[pc];
    assign instr_opcode = instruction[18:16];
    assign instr_reg_a = instruction[15:12];
    assign instr_reg_b = instruction[11:8];
    assign instr_dest1 = instruction[7:4];
    assign instr_dest2 = instruction[3:0];
    
    // Registros de pipeline
    reg [2:0] saved_opcode;
    reg [3:0] saved_dest1;
    reg [3:0] saved_dest2;
    
    // Estados de la FSM de control
    localparam S_IDLE   = 3'd0;
    localparam S_LOAD   = 3'd1;
    localparam S_FETCH  = 3'd2;  // Aplicar selectores, leer registros
    localparam S_EXEC   = 3'd3;  // Evaluar flags, escribir, calcular next PC
    localparam S_DONE   = 3'd4;
    
    reg [2:0] state;
    
    // Cargar programa desde archivo
    initial begin
        $readmemh(PROGRAM_FILE, program_rom);
    end
    
    // Lógica de control
    always @(posedge clk or negedge rst_n) begin
        if (!rst_n) begin
            state <= S_IDLE;
            pc <= 0;
            done <= 0;
            opcode <= 0;
            reg_a_sel <= 0;
            reg_b_sel <= 0;
            dest_reg <= 0;
            reg_write <= 0;
            load_operands <= 0;
            saved_opcode <= 0;
            saved_dest1 <= 0;
            saved_dest2 <= 0;
        end else begin
            case (state)
                S_IDLE: begin
                    done <= 0;
                    load_operands <= 0;
                    reg_write <= 0;
                    if (start) begin
                        state <= S_LOAD;
                        load_operands <= 1;
                    end
                end
                
                S_LOAD: begin
                    // Cargar operandos en el mismo ciclo
                    load_operands <= 0;
                    pc <= 0;
                    state <= S_FETCH;
                end
                
                S_FETCH: begin
                    // Aplicar selectores de registro y guardar info de instrucción
                    reg_a_sel <= instr_reg_a;
                    reg_b_sel <= instr_reg_b;
                    dest_reg <= instr_dest1;
                    opcode <= instr_opcode;
                    
                    // Guardar para el siguiente ciclo
                    saved_opcode <= instr_opcode;
                    saved_dest1 <= instr_dest1;
                    saved_dest2 <= instr_dest2;
                    
                    reg_write <= 0;  // No escribir aún
                    
                    // Ir a EXECUTE (los flags se evaluarán con los selectores correctos)
                    state <= S_EXEC;
                end
                
                S_EXEC: begin
                    // Ahora los flags reflejan los valores correctos de los registros
                    case (saved_opcode)
                        OP_ADD, OP_SUB, OP_SHL, OP_SHR, OP_MOV: begin
                            // Escribir resultado
                            reg_write <= 1;
                            pc <= saved_dest2;
                            state <= S_FETCH;
                        end
                        
                        OP_BGT: begin
                            reg_write <= 0;
                            if (greater_flag)
                                pc <= saved_dest1;
                            else
                                pc <= saved_dest2;
                            state <= S_FETCH;
                        end
                        
                        OP_BEQ: begin
                            reg_write <= 0;
                            if (equal_flag)
                                pc <= saved_dest1;
                            else
                                pc <= saved_dest2;
                            state <= S_FETCH;
                        end
                        
                        OP_HALT: begin
                            reg_write <= 0;
                            state <= S_DONE;
                        end
                        
                        default: begin
                            reg_write <= 0;
                            state <= S_DONE;
                        end
                    endcase
                end
                
                S_DONE: begin
                    done <= 1;
                    reg_write <= 0;
                    if (start) begin
                        state <= S_LOAD;
                        load_operands <= 1;
                        done <= 0;
                    end
                end
            endcase
        end
    end

endmodule

hdl/simple_cpu_top.v
// Módulo Top para SimpleCPU
// Conecta la unidad de control con el datapath

module simple_cpu_top #(
    parameter BIT_WIDTH = 16,
    parameter PROGRAM_FILE = "program.mem"
)(
    input wire clk,
    input wire rst_n,
    input wire start,
    input wire [BIT_WIDTH-1:0] operand_a,
    input wire [BIT_WIDTH-1:0] operand_b,
    output wire [BIT_WIDTH-1:0] result,
    output wire done,
    output wire [3:0] pc
);

    // Señales internas
    wire [2:0] opcode;
    wire [3:0] reg_a_sel;
    wire [3:0] reg_b_sel;
    wire [3:0] dest_reg;
    wire reg_write;
    wire load_operands;
    
    wire [BIT_WIDTH-1:0] reg_a_val;
    wire [BIT_WIDTH-1:0] reg_b_val;
    wire [BIT_WIDTH-1:0] alu_result;
    wire zero_flag;
    wire equal_flag;
    wire greater_flag;
    
    // Instanciar Unidad de Control
    simple_control #(
        .PROGRAM_FILE(PROGRAM_FILE)
    ) control (
        .clk(clk),
        .rst_n(rst_n),
        .start(start),
        .zero_flag(zero_flag),
        .equal_flag(equal_flag),
        .greater_flag(greater_flag),
        .opcode(opcode),
        .reg_a_sel(reg_a_sel),
        .reg_b_sel(reg_b_sel),
        .dest_reg(dest_reg),
        .reg_write(reg_write),
        .load_operands(load_operands),
        .pc(pc),
        .done(done)
    );
    
    // Instanciar Datapath
    simple_datapath #(
        .BIT_WIDTH(BIT_WIDTH)
    ) datapath (
        .clk(clk),
        .rst_n(rst_n),
        .opcode(opcode),
        .reg_a_sel(reg_a_sel),
        .reg_b_sel(reg_b_sel),
        .dest_reg(dest_reg),
        .reg_write(reg_write),
        .load_operands(load_operands),
        .operand_a_in(operand_a),
        .operand_b_in(operand_b),
        .reg_a_val(reg_a_val),
        .reg_b_val(reg_b_val),
        .result_out(alu_result),
        .zero_flag(zero_flag),
        .equal_flag(equal_flag),
        .greater_flag(greater_flag)
    );
    

    assign result = datapath.registers[10];

endmodule

hdl/simple_cpu_tb.v
`timescale 1ns/1ps

// Testbench para SimpleCPU con memoria de programa
module simple_cpu_tb;
    parameter BIT_WIDTH = 16;
    parameter CLK_PERIOD = 10;
    
    // Señales
    reg clk;
    reg rst_n;
    reg start;
    reg [BIT_WIDTH-1:0] operand_a;
    reg [BIT_WIDTH-1:0] operand_b;
    wire [BIT_WIDTH-1:0] result;
    wire done;
    wire [3:0] pc;
    
    // Instanciar DUT
    simple_cpu_top #(
        .BIT_WIDTH(BIT_WIDTH),
        .PROGRAM_FILE("hdl/program.mem")
    ) dut (
        .clk(clk),
        .rst_n(rst_n),
        .start(start),
        .operand_a(operand_a),
        .operand_b(operand_b),
        .result(result),
        .done(done),
        .pc(pc)
    );
    
    // Generador de reloj
    initial begin
        clk = 0;
        forever #(CLK_PERIOD/2) clk = ~clk;
    end
    
    // Variables de test
    integer test_count;
    integer error_count;
    integer cycles;
    reg [BIT_WIDTH-1:0] expected;
    
    // Task para ejecutar una multiplicación
    task run_multiply;
        input [BIT_WIDTH-1:0] a;
        input [BIT_WIDTH-1:0] b;
        input [BIT_WIDTH-1:0] exp;
        begin
            test_count = test_count + 1;
            operand_a = a;
            operand_b = b;
            expected = exp;
            cycles = 0;
            
            // Pulso de start
            @(posedge clk);
            start = 1;
            @(posedge clk);
            start = 0;
            
            // Esperar done o timeout
            while (!done && cycles < 500) begin
                @(posedge clk);
                cycles = cycles + 1;
                if (cycles < 20)
                    $display("  Cycle %0d: PC=%0d, state=%0d, opcode=%0d, done=%0d", 
                             cycles, pc, dut.control.state, dut.control.opcode, done);
            end
            
            // Verificar resultado
            if (!done) begin
                $display("Test #%0d: %0d * %0d - ERROR: Timeout after %0d cycles", 
                         test_count, a, b, cycles);
                error_count = error_count + 1;
            end else if (result !== exp) begin
                $display("Test #%0d: %0d * %0d = %0d (expected %0d) - FAILED [%0d cycles]", 
                         test_count, a, b, result, exp, cycles);
                error_count = error_count + 1;
            end else begin
                $display("Test #%0d: %0d * %0d = %0d - PASSED [%0d cycles]", 
                         test_count, a, b, result, cycles);
            end
            
            // Reset para siguiente test
            rst_n = 0;
            @(posedge clk);
            @(posedge clk);
            rst_n = 1;
            @(posedge clk);
        end
    endtask
    
    // Test principal
    initial begin
        $dumpfile("simple_cpu_tb.vcd");
        $dumpvars(0, simple_cpu_tb);
        
        $display("========================================");
        $display("Testbench: SimpleCPU con ROM de Programa");
        $display("Bit width: %0d", BIT_WIDTH);
        $display("========================================\n");
        
        // Inicializar
        test_count = 0;
        error_count = 0;
        rst_n = 0;
        start = 0;
        operand_a = 0;
        operand_b = 0;
        
        // Reset
        #(CLK_PERIOD * 3);
        rst_n = 1;
        #(CLK_PERIOD * 2);
        
        // === Casos básicos ===
        $display("--- Casos básicos ---");
        run_multiply(3, 5, 15);
        run_multiply(7, 8, 56);
        run_multiply(12, 10, 120);
        
        // === Casos con cero ===
        $display("\n--- Casos con cero ---");
        run_multiply(0, 5, 0);
        run_multiply(5, 0, 0);
        
        // === Casos con uno ===
        $display("\n--- Casos con uno ---");
        run_multiply(1, 42, 42);
        run_multiply(42, 1, 42);
        
        // === Casos más grandes ===
        $display("\n--- Casos grandes ---");
        run_multiply(15, 15, 225);
        run_multiply(100, 2, 200);
        run_multiply(255, 255, 65025);
        
        // === Resumen ===
        $display("\n========================================");
        $display("Testbench completado");
        $display("Total tests: %0d", test_count);
        $display("Errores: %0d", error_count);
        if (error_count == 0)
            $display("RESULTADO: TODOS LOS TESTS PASARON ✓");
        else
            $display("RESULTADO: %0d TESTS FALLARON ✗", error_count);
        $display("========================================\n");
        
        $finish;
    end

endmodule

simple_cpu_tb.vcd
$date
	Fri Feb  6 11:24:29 2026
$end
$version
	Icarus Verilog
$end
$timescale
	1ps
$end
$scope module simple_cpu_tb $end
$var wire 16 ! result [15:0] $end
$var wire 4 " pc [3:0] $end
$var wire 1 # done $end
$var reg 1 $ clk $end
$var reg 16 % expected [15:0] $end
$var reg 16 & operand_a [15:0] $end
$var reg 16 ' operand_b [15:0] $end
$var reg 1 ( rst_n $end
$var reg 1 ) start $end
$var integer 32 * cycles [31:0] $end
$var integer 32 + error_count [31:0] $end
$var integer 32 , test_count [31:0] $end
$scope module dut $end
$var wire 1 $ clk $end
$var wire 16 - operand_a [15:0] $end
$var wire 16 . operand_b [15:0] $end
$var wire 16 / result [15:0] $end
$var wire 1 ( rst_n $end
$var wire 1 ) start $end
$var wire 1 0 zero_flag $end
$var wire 1 1 reg_write $end
$var wire 16 2 reg_b_val [15:0] $end
$var wire 4 3 reg_b_sel [3:0] $end
$var wire 16 4 reg_a_val [15:0] $end
$var wire 4 5 reg_a_sel [3:0] $end
$var wire 4 6 pc [3:0] $end
$var wire 3 7 opcode [2:0] $end
$var wire 1 8 load_operands $end
$var wire 1 9 greater_flag $end
$var wire 1 : equal_flag $end
$var wire 1 # done $end
$var wire 4 ; dest_reg [3:0] $end
$var wire 16 < alu_result [15:0] $end
$scope module control $end
$var wire 1 $ clk $end
$var wire 19 = instruction [18:0] $end
$var wire 1 ( rst_n $end
$var wire 1 ) start $end
$var wire 1 0 zero_flag $end
$var wire 4 > instr_reg_b [3:0] $end
$var wire 4 ? instr_reg_a [3:0] $end
$var wire 3 @ instr_opcode [2:0] $end
$var wire 4 A instr_dest2 [3:0] $end
$var wire 4 B instr_dest1 [3:0] $end
$var wire 1 9 greater_flag $end
$var wire 1 : equal_flag $end
$var reg 4 C dest_reg [3:0] $end
$var reg 1 # done $end
$var reg 1 8 load_operands $end
$var reg 3 D opcode [2:0] $end
$var reg 4 E pc [3:0] $end
$var reg 4 F reg_a_sel [3:0] $end
$var reg 4 G reg_b_sel [3:0] $end
$var reg 1 1 reg_write $end
$var reg 4 H saved_dest1 [3:0] $end
$var reg 4 I saved_dest2 [3:0] $end
$var reg 3 J saved_opcode [2:0] $end
$var reg 3 K state [2:0] $end
$upscope $end
$scope module datapath $end
$var wire 1 $ clk $end
$var wire 4 L dest_reg [3:0] $end
$var wire 1 8 load_operands $end
$var wire 3 M opcode [2:0] $end
$var wire 16 N operand_a_in [15:0] $end
$var wire 16 O operand_b_in [15:0] $end
$var wire 4 P reg_a_sel [3:0] $end
$var wire 16 Q reg_a_val [15:0] $end
$var wire 4 R reg_b_sel [3:0] $end
$var wire 16 S reg_b_val [15:0] $end
$var wire 1 1 reg_write $end
$var wire 16 T result_out [15:0] $end
$var wire 1 ( rst_n $end
$var wire 1 0 zero_flag $end
$var wire 1 9 greater_flag $end
$var wire 1 : equal_flag $end
$var reg 16 U alu_result [15:0] $end
$var integer 32 V i [31:0] $end
$upscope $end
$upscope $end
$scope task run_multiply $end
$var reg 16 W a [15:0] $end
$var reg 16 X b [15:0] $end
$var reg 16 Y exp [15:0] $end
$upscope $end
$upscope $end
$enddefinitions $end
#0
$dumpvars
bx Y
bx X
bx W
b10000 V
b0 U
b0 T
b0 S
b0 R
b0 Q
b0 P
b0 O
b0 N
b0 M
b0 L
b0 K
b0 J
b0 I
b0 H
b0 G
b0 F
b0 E
b0 D
b0 C
b1000 B
b1 A
b110 @
b1001 ?
b0 >
b1101001000010000001 =
b0 <
b0 ;
1:
09
08
b0 7
b0 6
b0 5
b0 4
b0 3
b0 2
01
10
b0 /
b0 .
b0 -
b0 ,
b0 +
bx *
0)
0(
b0 '
b0 &
bx %
0$
0#
b0 "
b0 !
$end
#5000
b10000 V
1$
#10000
0$
#15000
b10000 V
1$
#20000
0$
#25000
b10000 V
1$
#30000
0$
1(
#35000
1$
#40000
0$
#45000
1$
#50000
0$
b0 *
b1111 %
b101 '
b101 .
b101 O
b11 &
b11 -
b11 N
b1 ,
b1111 Y
b101 X
b11 W
#55000
18
b1 K
1)
1$
#60000
0$
#65000
b10 K
08
0)
1$
#70000
0$
#75000
b11 K
b1 I
b1000 H
b110 J
b110 7
b110 D
b110 M
b1000 ;
b1000 C
b1000 L
0:
19
b101 4
b101 Q
b1001 5
b1001 F
b1001 P
b1 *
1$
#80000
0$
#85000
b100 @
b1011 B
b10 A
b10 K
b1001001000010110010 =
b1 "
b1 6
b1 E
b10 *
1$
#90000
0$
#95000
b101 <
b101 T
b101 U
b11 K
b10 I
b1011 H
b100 J
b100 7
b100 D
b100 M
b1011 ;
b1011 C
b1011 L
b11 *
1$
#100000
0$
#105000
b11 @
b1011 ?
b1 >
b11 A
b10 K
b111011000110110011 =
b10 "
b10 6
b10 E
11
b100 *
1$
#110000
0$
#115000
b10 <
b10 T
b10 U
b11 K
01
b11 I
b11 J
b11 7
b11 D
b11 M
00
b1 2
b1 S
b1 3
b1 G
b1 R
b1011 5
b1011 F
b1011 P
b101 *
1$
#120000
0$
#125000
b10 @
b100 A
b10 K
b101011000110110100 =
b11 "
b11 6
b11 E
11
b110 *
1$
#130000
0$
#135000
b100 <
b100 T
b100 U
b11 K
01
b100 I
b10 J
b10 7
b10 D
b10 M
b10 4
b10 Q
b111 *
1$
#140000
0$
#145000
b110 @
b1001 >
b110 B
b101 A
b10 K
b1101011100101100101 =
b100 "
b100 6
b100 E
11
b1000 *
1$
#150000
0$
#155000
b0 <
b0 T
b0 U
b11 K
01
b101 I
b110 H
b110 J
b110 7
b110 D
b110 M
b110 ;
b110 C
b110 L
09
b101 2
b101 S
b1001 3
b1001 G
b1001 R
b100 4
b100 Q
b1001 *
1$
#160000
0$
#165000
b0 @
b1010 ?
b1000 >
b1010 B
b110 A
b10 K
b1010100010100110 =
b101 "
b101 6
b101 E
b1010 *
1$
#170000
0$
#175000
b11 <
b11 T
b11 U
b11 K
b110 I
b1010 H
b0 J
b0 7
b0 D
b0 M
b1010 ;
b1010 C
b1010 L
b11 2
b11 S
b1000 3
b1000 G
b1000 R
b0 4
b0 Q
b1010 5
b1010 F
b1010 P
b1011 *
1$
#180000
0$
#185000
b10 @
b1000 ?
b1 >
b1000 B
b111 A
b10 K
b101000000110000111 =
b110 "
b110 6
b110 E
11
b1100 *
1$
#190000
0$
#195000
b110 <
b110 T
b110 U
b11 K
01
b111 I
b1000 H
b10 J
b10 7
b10 D
b10 M
b1000 ;
b1000 C
b1000 L
19
b1 2
b1 S
b1 3
b1 G
b1 R
b1000 5
b1000 F
b1000 P
0:
b11 4
b11 Q
b11 !
b11 /
b1101 *
1$
#200000
0$
#205000
b11 @
b1001 ?
b1001 B
b0 A
b10 K
b111001000110010000 =
b111 "
b111 6
b111 E
11
b1110 *
1$
#210000
0$
#215000
b10 <
b10 T
b10 U
b11 K
01
b0 I
b1001 H
b11 J
b11 7
b11 D
b11 M
b1001 ;
b1001 C
b1001 L
b1001 5
b1001 F
b1001 P
b101 4
b101 Q
b1111 *
1$
#220000
0$
#225000
b110 @
b0 >
b1000 B
b1 A
b10 K
b1101001000010000001 =
b0 "
b0 6
b0 E
11
b10000 *
1$
#230000
0$
#235000
b0 <
b0 T
b0 U
b11 K
01
b1 I
b1000 H
b110 J
b110 7
b110 D
b110 M
b1000 ;
b1000 C
b1000 L
10
b0 2
b0 S
b0 3
b0 G
b0 R
b10 4
b10 Q
b10001 *
1$
#240000
0$
#245000
b100 @
b1011 B
b10 A
b10 K
b1001001000010110010 =
b1 "
b1 6
b1 E
b10010 *
1$
#250000
0$
#255000
b10 <
b10 T
b10 U
b11 K
b10 I
b1011 H
b100 J
b100 7
b100 D
b100 M
b1011 ;
b1011 C
b1011 L
b10011 *
1$
#260000
0$
#265000
b11 @
b1011 ?
b1 >
b11 A
b10 K
b111011000110110011 =
b10 "
b10 6
b10 E
11
b10100 *
1$
#270000
0$
#275000
b1 <
b1 T
b1 U
b11 K
01
b11 I
b11 J
b11 7
b11 D
b11 M
00
b1 2
b1 S
b1 3
b1 G
b1 R
b1011 5
b1011 F
b1011 P
b10101 *
1$
#280000
0$
#285000
b10 @
b100 A
b10 K
b101011000110110100 =
b11 "
b11 6
b11 E
11
b10110 *
1$
#290000
0$
#295000
b10 <
b10 T
b10 U
b11 K
01
b100 I
b10 J
b10 7
b10 D
b10 M
1:
09
b1 4
b1 Q
b10111 *
1$
#300000
0$
#305000
b110 @
b1001 >
b110 B
b101 A
b10 K
b1101011100101100101 =
b100 "
b100 6
b100 E
11
b11000 *
1$
#310000
0$
#315000
b0 <
b0 T
b0 U
b11 K
01
b101 I
b110 H
b110 J
b110 7
b110 D
b110 M
b110 ;
b110 C
b110 L
b10 2
b10 S
b1001 3
b1001 G
b1001 R
1:
09
b10 4
b10 Q
b11001 *
1$
#320000
0$
#325000
b10 @
b1000 ?
b1 >
b1000 B
b111 A
b10 K
b101000000110000111 =
b110 "
b110 6
b110 E
b11010 *
1$
#330000
0$
#335000
b1100 <
b1100 T
b1100 U
b11 K
b111 I
b1000 H
b10 J
b10 7
b10 D
b10 M
b1000 ;
b1000 C
b1000 L
b1 2
b1 S
b1 3
b1 G
b1 R
0:
19
b110 4
b110 Q
b1000 5
b1000 F
b1000 P
b11011 *
1$
#340000
0$
#345000
b11 @
b1001 ?
b1001 B
b0 A
b10 K
b111001000110010000 =
b111 "
b111 6
b111 E
11
b11100 *
1$
#350000
0$
#355000
b1 <
b1 T
b1 U
b11 K
01
b0 I
b1001 H
b11 J
b11 7
b11 D
b11 M
b1001 ;
b1001 C
b1001 L
b1001 5
b1001 F
b1001 P
b10 4
b10 Q
b11101 *
1$
#360000
0$
#365000
b110 @
b0 >
b1000 B
b1 A
b10 K
b1101001000010000001 =
b0 "
b0 6
b0 E
11
b11110 *
1$
#370000
0$
#375000
b0 <
b0 T
b0 U
b11 K
01
b1 I
b1000 H
b110 J
b110 7
b110 D
b110 M
b1000 ;
b1000 C
b1000 L
10
b0 2
b0 S
b0 3
b0 G
b0 R
0:
19
b1 4
b1 Q
b11111 *
1$
#380000
0$
#385000
b100 @
b1011 B
b10 A
b10 K
b1001001000010110010 =
b1 "
b1 6
b1 E
b100000 *
1$
#390000
0$
#395000
b1 <
b1 T
b1 U
b11 K
b10 I
b1011 H
b100 J
b100 7
b100 D
b100 M
b1011 ;
b1011 C
b1011 L
b100001 *
1$
#400000
0$
#405000
b11 @
b1011 ?
b1 >
b11 A
b10 K
b111011000110110011 =
b10 "
b10 6
b10 E
11
b100010 *
1$
#410000
0$
#415000
b0 <
b0 T
b0 U
b11 K
01
b11 I
b11 J
b11 7
b11 D
b11 M
00
1:
09
b1 2
b1 S
b1 3
b1 G
b1 R
b1011 5
b1011 F
b1011 P
b100011 *
1$
#420000
0$
#425000
b10 @
b100 A
b10 K
b101011000110110100 =
b11 "
b11 6
b11 E
11
b100100 *
1$
#430000
0$
#435000
b11 K
01
b100 I
b10 J
b10 7
b10 D
b10 M
0:
b0 4
b0 Q
b100101 *
1$
#440000
0$
#445000
b110 @
b1001 >
b110 B
b101 A
b10 K
b1101011100101100101 =
b100 "
b100 6
b100 E
11
b100110 *
1$
#450000
0$
#455000
b11 K
01
b101 I
b110 H
b110 J
b110 7
b110 D
b110 M
b110 ;
b110 C
b110 L
b1001 3
b1001 G
b1001 R
b100111 *
1$
#460000
0$
#465000
b0 @
b1010 ?
b1000 >
b1010 B
b110 A
b10 K
b1010100010100110 =
b101 "
b101 6
b101 E
b101000 *
1$
#470000
0$
#475000
b1111 <
b1111 T
b1111 U
b11 K
b110 I
b1010 H
b0 J
b0 7
b0 D
b0 M
b1010 ;
b1010 C
b1010 L
b1100 2
b1100 S
b1000 3
b1000 G
b1000 R
09
b11 4
b11 Q
b1010 5
b1010 F
b1010 P
b101001 *
1$
#480000
0$
#485000
b10 @
b1000 ?
b1 >
b1000 B
b111 A
b10 K
b101000000110000111 =
b110 "
b110 6
b110 E
11
b101010 *
1$
#490000
0$
#495000
b11000 <
b11000 T
b11000 U
b11 K
01
b111 I
b1000 H
b10 J
b10 7
b10 D
b10 M
b1000 ;
b1000 C
b1000 L
b1 2
b1 S
b1 3
b1 G
b1 R
0:
b1000 5
b1000 F
b1000 P
19
b1100 4
b1100 Q
b1111 !
b1111 /
b101011 *
1$
#500000
0$
#505000
b11 @
b1001 ?
b1001 B
b0 A
b10 K
b111001000110010000 =
b111 "
b111 6
b111 E
11
b101100 *
1$
#510000
0$
#515000
b0 <
b0 T
b0 U
b11 K
01
b0 I
b1001 H
b11 J
b11 7
b11 D
b11 M
b1001 ;
b1001 C
b1001 L
1:
09
b1001 5
b1001 F
b1001 P
b1 4
b1 Q
b101101 *
1$
#520000
0$
#525000
b110 @
b0 >
b1000 B
b1 A
b10 K
b1101001000010000001 =
b0 "
b0 6
b0 E
11
b101110 *
1$
#530000
0$
#535000
b11 K
01
b1 I
b1000 H
b110 J
b110 7
b110 D
b110 M
b1000 ;
b1000 C
b1000 L
10
b0 2
b0 S
b0 3
b0 G
b0 R
1:
b0 4
b0 Q
b101111 *
1$
#540000
0$
#545000
b111 @
b0 ?
b0 B
b0 A
b10 K
b1110000000000000000 =
b1000 "
b1000 6
b1000 E
b110000 *
1$
#550000
0$
#555000
b11 K
b0 I
b0 H
b111 J
b111 7
b111 D
b111 M
b0 ;
b0 C
b0 L
b0 5
b0 F
b0 P
b110001 *
1$
#560000
0$
#565000
b100 K
b110010 *
1$
#570000
0$
#575000
1#
b110011 *
1$
#580000
0$
#585000
b110 @
b1001 ?
b1000 B
b1 A
b0 !
b0 /
b0 J
b0 7
b0 D
b0 M
0#
b1101001000010000001 =
b0 "
b0 6
b0 E
b0 K
b10000 V
0(
b110100 *
1$
#590000
0$
#595000
b10000 V
1$
#600000
0$
#605000
1(
1$
#610000
0$
#615000
b0 *
b111000 %
b1000 '
b1000 .
b1000 O
b111 &
b111 -
b111 N
b10 ,
b111000 Y
b1000 X
b111 W
1$
#620000
0$
#625000
18
b1 K
1)
1$
#630000
0$
#635000
b10 K
08
0)
1$
#640000
0$
#645000
b11 K
b1 I
b1000 H
b110 J
b110 7
b110 D
b110 M
b1000 ;
b1000 C
b1000 L
0:
19
b1000 4
b1000 Q
b1001 5
b1001 F
b1001 P
b1 *
1$
#650000
0$
#655000
b100 @
b1011 B
b10 A
b10 K
b1001001000010110010 =
b1 "
b1 6
b1 E
b10 *
1$
#660000
0$
#665000
b1000 <
b1000 T
b1000 U
b11 K
b10 I
b1011 H
b100 J
b100 7
b100 D
b100 M
b1011 ;
b1011 C
b1011 L
b11 *
1$
#670000
0$
#675000
b11 @
b1011 ?
b1 >
b11 A
b10 K
b111011000110110011 =
b10 "
b10 6
b10 E
11
b100 *
1$
#680000
0$
#685000
b100 <
b100 T
b100 U
b11 K
01
b11 I
b11 J
b11 7
b11 D
b11 M
00
b1 2
b1 S
b1 3
b1 G
b1 R
0:
19
b1000 4
b1000 Q
b1011 5
b1011 F
b1011 P
b101 *
1$
#690000
0$
#695000
b10 @
b100 A
b10 K
b101011000110110100 =
b11 "
b11 6
b11 E
11
b110 *
1$
#700000
0$
#705000
b1000 <
b1000 T
b1000 U
b100 4
b100 Q
b11 K
01
b100 I
b10 J
b10 7
b10 D
b10 M
b111 *
1$
#710000
0$
#715000
b110 @
b1001 >
b110 B
b101 A
b10 K
b1101011100101100101 =
b100 "
b100 6
b100 E
11
b1000 *
1$
#720000
0$
#725000
b0 <
b0 T
b0 U
1:
b1000 4
b1000 Q
b11 K
01
b101 I
b110 H
b110 J
b110 7
b110 D
b110 M
b110 ;
b110 C
b110 L
09
b1000 2
b1000 S
b1001 3
b1001 G
b1001 R
b1001 *
1$
#730000
0$
#735000
b10 @
b1000 ?
b1 >
b1000 B
b111 A
b10 K
b101000000110000111 =
b110 "
b110 6
b110 E
b1010 *
1$
#740000
0$
#745000
b1110 <
b1110 T
b1110 U
b11 K
b111 I
b1000 H
b10 J
b10 7
b10 D
b10 M
b1000 ;
b1000 C
b1000 L
19
b1 2
b1 S
b1 3
b1 G
b1 R
0:
b111 4
b111 Q
b1000 5
b1000 F
b1000 P
b1011 *
1$
#750000
0$
#755000
b11 @
b1001 ?
b1001 B
b0 A
b10 K
b111001000110010000 =
b111 "
b111 6
b111 E
11
b1100 *
1$
#760000
0$
#765000
b100 <
b100 T
b100 U
b11 K
01
b0 I
b1001 H
b11 J
b11 7
b11 D
b11 M
b1001 ;
b1001 C
b1001 L
b1000 4
b1000 Q
b1001 5
b1001 F
b1001 P
b1101 *
1$
#770000
0$
#775000
b110 @
b0 >
b1000 B
b1 A
b10 K
b1101001000010000001 =
b0 "
b0 6
b0 E
11
b1110 *
1$
#780000
0$
